verilog/rtl/dff.v
`timescale 1ns / 1ps

module dff #(parameter WIDTH = 1) (
    input clk, 
    input reset, 
    input [WIDTH-1:0] d, 
    output reg [WIDTH-1:0] q
);
    always @(posedge clk or posedge reset)
        if (reset)
            q <= 0; 
        else
            q <= d;
endmodule

verilog/rtl/tff.v
`timescale 1ns / 1ps

module tff (
    input clk,   
    input reset, 
    input t,         
    output reg q      
);

    always @(posedge clk or posedge reset) begin
        if (reset)
            q <= 1'b0; 
        else if (t)
            q <= ~q;  
    end
endmodule

verilog/rtl/async_down_counter.v
`timescale 1ns / 1ps

module async_down_counter(
    input clk,         
    input reset,       
    output [7:0] q     
);
    wire q0, q1, q2, q3, q4, q5, q6, q7;

    tff tff0 (.clk(clk), .reset(reset), .t(1'b1), .q(q0));
    tff tff1 (.clk(~q0), .reset(reset), .t(1'b1), .q(q1));
    tff tff2 (.clk(~q1), .reset(reset), .t(1'b1), .q(q2));
    tff tff3 (.clk(~q2), .reset(reset), .t(1'b1), .q(q3));
    tff tff4 (.clk(~q3), .reset(reset), .t(1'b1), .q(q4));
    tff tff5 (.clk(~q4), .reset(reset), .t(1'b1), .q(q5));
    tff tff6 (.clk(~q5), .reset(reset), .t(1'b1), .q(q6));
    tff tff7 (.clk(~q6), .reset(reset), .t(1'b1), .q(q7));

    assign q = {q7, q6, q5, q4, q3, q2, q1, q0};
endmodule

verilog/rtl/cla_4bit.v
`timescale 1ns / 1ps

module cla_4bit (
    input clk, 
    input reset,
    output [3:0] B, A,
    output Cout,
    output [3:0] Sum
);
    wire [3:0] A_sync, B_sync; 
    wire [3:0] Sum_unsync;      
    wire Cout_unsync;
    wire [3:0] P, G;
    wire [3:1] C;
    wire [8:0] t;
    wire [7:0] clk_div;
    
    async_down_counter async_down_counter_A(.clk(clk), .reset(reset), .q(clk_div));

    dff #(4) DFF_A (.clk(clk), .reset(reset), .d(clk_div[3:0]), .q(A_sync));
    dff #(4) DFF_B (.clk(clk), .reset(reset), .d(clk_div[7:4]), .q(B_sync));

    xor xor1(P[0], A_sync[0], B_sync[0]);
    xor xor2(P[1], A_sync[1], B_sync[1]);
    xor xor3(P[2], A_sync[2], B_sync[2]);
    xor xor4(P[3], A_sync[3], B_sync[3]);
    and and1(G[0], A_sync[0], B_sync[0]);
    and and2(G[1], A_sync[1], B_sync[1]);
    and and3(G[2], A_sync[2], B_sync[2]);
    and and4(G[3], A_sync[3], B_sync[3]);

    assign C[1] = G[0];
    and and5(t[0], P[1], G[0]);
    or or1(C[2], G[1], t[0]); 
    and and6(t[1], P[2], t[0]);
    and and7(t[2], P[2], G[1]);
    or or2(t[3], t[2], t[1]);
    or or3(C[3], G[2], t[3]);
    and and8(t[4], P[3], t[1]);
    and and9(t[5], P[3], t[2]);
    and and10(t[6], P[3], G[2]);
    or or4(t[7], t[5], t[4]);
    or or5(t[8], G[3], t[6]);
    or or6(Cout_unsync, t[8], t[7]);

    assign Sum_unsync[0] = P[0];
    xor xor5(Sum_unsync[1], P[1], C[1]);
    xor xor6(Sum_unsync[2], P[2], C[2]);
    xor xor7(Sum_unsync[3], P[3], C[3]);
    
//        // Propagate and Generate signals
//    assign P = A_sync ^ B_sync;
//    assign G = A_sync & B_sync;

//    // Carry Look-Ahead Logic (assuming Cin = 0)
//    assign C[1] = G[0];
//    assign C[2] = G[1] | (P[1] & G[0]);
//    assign C[3] = G[2] | (P[2] & G[1]) | (P[2] & P[1] & G[0]);
//    assign Cout_unsync = G[3] | (P[3] & G[2]) | (P[3] & P[2] & G[1]) | (P[3] & P[2] & P[1] & G[0]);

//    // Sum calculation
//    assign Sum_unsync[0] = P[0];
//    assign Sum_unsync[1] = P[1] ^ C[1];
//    assign Sum_unsync[2] = P[2] ^ C[2];
//    assign Sum_unsync[3] = P[3] ^ C[3];

    // Output D Flip-Flops with reset
    dff #(4) DFF_Sum (.clk(clk), .reset(reset), .d(Sum_unsync), .q(Sum));
    dff #(1) DFF_Cout (.clk(clk), .reset(reset), .d(Cout_unsync), .q(Cout));
    
    assign A = clk_div[3:0];
    assign B = clk_div[7:4];
endmodule

verilog/tb/cla_4bit_tb.v
`timescale 1ns / 1ps

module cla_4bit_tb;
    reg clk;
    reg reset;
    wire [3:0] B, A;
    wire Cout;
    wire [3:0] Sum;

    cla_4bit dut (
        .clk(clk),
        .reset(reset),
        .B(B),
        .A(A),
        .Cout(Cout),
        .Sum(Sum)
    );

    initial begin
        $dumpfile("cla_4bit_tb.vcd");
        $dumpvars(0,cla_4bit_tb);
        clk = 0;
        #1;
        reset = 1;#2;
        reset = 0;
        #2572;
        $finish;
    end

    always #5 clk = ~clk;
    always@(*)
    $monitor("time = %t \t clk = %d \t reset = %d \t B = %d \t A = %d \t Cout = %d \t Sum = %d",$time,clk,reset,B,A,Cout,Sum);
endmodule

verilog/sim/cla_4bit_tb.vcd
$date
	Wed Nov 20 17:34:01 2024
$end
$version
	Icarus Verilog
$end
$timescale
	1ps
$end
$scope module cla_4bit_tb $end
$var wire 4 ! Sum [3:0] $end
$var wire 1 " Cout $end
$var wire 4 # B [3:0] $end
$var wire 4 $ A [3:0] $end
$var reg 1 % clk $end
$var reg 1 & reset $end
$scope module dut $end
$var wire 1 ' Cout_unsync $end
$var wire 1 % clk $end
$var wire 1 & reset $end
$var wire 9 ( t [8:0] $end
$var wire 8 ) clk_div [7:0] $end
$var wire 4 * Sum_unsync [3:0] $end
$var wire 4 + Sum [3:0] $end
$var wire 4 , P [3:0] $end
$var wire 4 - G [3:0] $end
$var wire 1 " Cout $end
$var wire 3 . C [3:1] $end
$var wire 4 / B_sync [3:0] $end
$var wire 4 0 B [3:0] $end
$var wire 4 1 A_sync [3:0] $end
$var wire 4 2 A [3:0] $end
$scope module DFF_A $end
$var wire 1 % clk $end
$var wire 4 3 d [3:0] $end
$var wire 1 & reset $end
$var reg 4 4 q [3:0] $end
$upscope $end
$scope module DFF_B $end
$var wire 1 % clk $end
$var wire 4 5 d [3:0] $end
$var wire 1 & reset $end
$var reg 4 6 q [3:0] $end
$upscope $end
$scope module DFF_Cout $end
$var wire 1 % clk $end
$var wire 1 ' d $end
$var wire 1 & reset $end
$var reg 1 " q $end
$upscope $end
$scope module DFF_Sum $end
$var wire 1 % clk $end
$var wire 4 7 d [3:0] $end
$var wire 1 & reset $end
$var reg 4 8 q [3:0] $end
$upscope $end
$scope module async_down_counter_A $end
$var wire 1 % clk $end
$var wire 1 & reset $end
$var wire 1 9 q7 $end
$var wire 1 : q6 $end
$var wire 1 ; q5 $end
$var wire 1 < q4 $end
$var wire 1 = q3 $end
$var wire 1 > q2 $end
$var wire 1 ? q1 $end
$var wire 1 @ q0 $end
$var wire 8 A q [7:0] $end
$scope module tff0 $end
$var wire 1 % clk $end
$var wire 1 & reset $end
$var wire 1 B t $end
$var reg 1 @ q $end
$upscope $end
$scope module tff1 $end
$var wire 1 C clk $end
$var wire 1 & reset $end
$var wire 1 D t $end
$var reg 1 ? q $end
$upscope $end
$scope module tff2 $end
$var wire 1 E clk $end
$var wire 1 & reset $end
$var wire 1 F t $end
$var reg 1 > q $end
$upscope $end
$scope module tff3 $end
$var wire 1 G clk $end
$var wire 1 & reset $end
$var wire 1 H t $end
$var reg 1 = q $end
$upscope $end
$scope module tff4 $end
$var wire 1 I clk $end
$var wire 1 & reset $end
$var wire 1 J t $end
$var reg 1 < q $end
$upscope $end
$scope module tff5 $end
$var wire 1 K clk $end
$var wire 1 & reset $end
$var wire 1 L t $end
$var reg 1 ; q $end
$upscope $end
$scope module tff6 $end
$var wire 1 M clk $end
$var wire 1 & reset $end
$var wire 1 N t $end
$var reg 1 : q $end
$upscope $end
$scope module tff7 $end
$var wire 1 O clk $end
$var wire 1 & reset $end
$var wire 1 P t $end
$var reg 1 9 q $end
$upscope $end
$upscope $end
$upscope $end
$upscope $end
$enddefinitions $end
#0
$dumpvars
1P
xO
1N
xM
1L
xK
1J
xI
1H
xG
1F
xE
1D
xC
1B
bx A
x@
x?
x>
x=
x<
x;
x:
x9
bx 8
bx 7
bx 6
bx 5
bx 4
bx 3
bx 2
bx 1
bx 0
bx /
bx .
bx -
bx ,
bx +
bx *
bx )
bx (
x'
x&
0%
bx $
bx #
x"
bx !
$end
#1000
0'
b0 (
b0 .
b0 *
b0 7
b0 -
b0 ,
1C
1E
1G
b0 $
b0 2
b0 3
1I
1K
1M
1O
b0 #
b0 0
b0 5
0@
b0 1
b0 4
b0 /
b0 6
b0 !
b0 +
b0 8
0"
0?
0>
0=
0<
0;
0:
b0 )
b0 A
09
1&
#3000
0&
#5000
b1 $
b1 2
b1 3
0C
b1 )
b1 A
1@
1%
#10000
0%
#15000
0E
1?
b1 *
b1 7
b1 ,
b10 $
b10 2
b10 3
1C
b10 )
b10 A
0@
b1 1
b1 4
1%
#20000
0%
#25000
b10 *
b10 7
b10 ,
b11 $
b11 2
b11 3
0C
b1 !
b1 +
b1 8
b10 1
b10 4
b11 )
b11 A
1@
1%
#30000
0%
#35000
0G
1>
1E
0?
b11 *
b11 7
b11 ,
b100 $
b100 2
b100 3
1C
b100 )
b100 A
0@
b11 1
b11 4
b10 !
b10 +
b10 8
1%
#40000
0%
#45000
b100 *
b100 7
b100 ,
b101 $
b101 2
b101 3
0C
b11 !
b11 +
b11 8
b100 1
b100 4
b101 )
b101 A
1@
1%
#50000
0%
#55000
0E
1?
b101 *
b101 7
b101 ,
b110 $
b110 2
b110 3
1C
b110 )
b110 A
0@
b101 1
b101 4
b100 !
b100 +
b100 8
1%
#60000
0%
#65000
b110 *
b110 7
b110 ,
b111 $
b111 2
b111 3
0C
b101 !
b101 +
b101 8
b110 1
b110 4
b111 )
b111 A
1@
1%
#70000
0%
#75000
0I
1=
1G
0>
1E
0?
b111 *
b111 7
b111 ,
b1000 $
b1000 2
b1000 3
1C
b1000 )
b1000 A
0@
b111 1
b111 4
b110 !
b110 +
b110 8
1%
#80000
0%
#85000
b1000 *
b1000 7
b1000 ,
b1001 $
b1001 2
b1001 3
0C
b111 !
b111 +
b111 8
b1000 1
b1000 4
b1001 )
b1001 A
1@
1%
#90000
0%
#95000
0E
1?
b1001 *
b1001 7
b1001 ,
b1010 $
b1010 2
b1010 3
1C
b1010 )
b1010 A
0@
b1001 1
b1001 4
b1000 !
b1000 +
b1000 8
1%
#100000
0%
#105000
b1010 *
b1010 7
b1010 ,
b1011 $
b1011 2
b1011 3
0C
b1001 !
b1001 +
b1001 8
b1010 1
b1010 4
b1011 )
b1011 A
1@
1%
#110000
0%
#115000
0G
1>
1E
0?
b1011 *
b1011 7
b1011 ,
b1100 $
b1100 2
b1100 3
1C
b1100 )
b1100 A
0@
b1011 1
b1011 4
b1010 !
b1010 +
b1010 8
1%
#120000
0%
#125000
b1100 *
b1100 7
b1100 ,
b1101 $
b1101 2
b1101 3
0C
b1011 !
b1011 +
b1011 8
b1100 1
b1100 4
b1101 )
b1101 A
1@
1%
#130000
0%
#135000
0E
1?
b1101 *
b1101 7
b1101 ,
b1110 $
b1110 2
b1110 3
1C
b1110 )
b1110 A
0@
b1101 1
b1101 4
b1100 !
b1100 +
b1100 8
1%
#140000
0%
#145000
b1110 *
b1110 7
b1110 ,
b1111 $
b1111 2
b1111 3
0C
b1101 !
b1101 +
b1101 8
b1110 1
b1110 4
b1111 )
b1111 A
1@
1%
#150000
0%
#155000
b1 #
b1 0
b1 5
0K
1<
1I
0=
1G
0>
1E
0?
b1111 *
b1111 7
b1111 ,
b0 $
b0 2
b0 3
1C
b10000 )
b10000 A
0@
b1111 1
b1111 4
b1110 !
b1110 +
b1110 8
1%
#160000
0%
#165000
b1 *
b1 7
b1 ,
b1 $
b1 2
b1 3
0C
b1111 !
b1111 +
b1111 8
b1 /
b1 6
b0 1
b0 4
b10001 )
b10001 A
1@
1%
#170000
0%
#175000
0E
1?
b1 .
b10 *
b10 7
b1 -
b0 ,
b10 $
b10 2
b10 3
1C
b10010 )
b10010 A
0@
b1 1
b1 4
b1 !
b1 +
b1 8
1%
#180000
0%
#185000
b0 .
b11 *
b11 7
b0 -
b11 ,
b11 $
b11 2
b11 3
0C
b10 !
b10 +
b10 8
b10 1
b10 4
b10011 )
b10011 A
1@
1%
#190000
0%
#195000
0G
1>
1E
0?
b1 (
b11 .
b100 *
b100 7
b1 -
b10 ,
b100 $
b100 2
b100 3
1C
b10100 )
b10100 A
0@
b11 1
b11 4
b11 !
b11 +
b11 8
1%
#200000
0%
#205000
b0 (
b0 .
b101 *
b101 7
b0 -
b101 ,
b101 $
b101 2
b101 3
0C
b100 !
b100 +
b100 8
b100 1
b100 4
b10101 )
b10101 A
1@
1%
#210000
0%
#215000
0E
1?
b1 .
b110 *
b110 7
b1 -
b100 ,
b110 $
b110 2
b110 3
1C
b10110 )
b10110 A
0@
b101 1
b101 4
b101 !
b101 +
b101 8
1%
#220000
0%
#225000
b0 .
b111 *
b111 7
b0 -
b111 ,
b111 $
b111 2
b111 3
0C
b110 !
b110 +
b110 8
b110 1
b110 4
b10111 )
b10111 A
1@
1%
#230000
0%
#235000
0I
1=
1G
0>
1E
0?
b1011 (
b111 .
b1000 *
b1000 7
b1 -
b110 ,
b1000 $
b1000 2
b1000 3
1C
b11000 )
b11000 A
0@
b111 1
b111 4
b111 !
b111 +
b111 8
1%
#240000
0%
#245000
0'
b0 (
b0 .
b1001 *
b1001 7
b0 -
b1001 ,
b1001 $
b1001 2
b1001 3
0C
b1000 !
b1000 +
b1000 8
b1000 1
b1000 4
b11001 )
b11001 A
1@
1%
#250000
0%
#255000
0E
1?
b1 .
b1010 *
b1010 7
b1 -
b1000 ,
b1010 $
b1010 2
b1010 3
1C
b11010 )
b11010 A
0@
b1001 1
b1001 4
b1001 !
b1001 +
b1001 8
1%
#260000
0%
#265000
b0 .
b1011 *
b1011 7
b0 -
b1011 ,
b1011 $
b1011 2
b1011 3
0C
b1010 !
b1010 +
b1010 8
b1010 1
b1010 4
b11011 )
b11011 A
1@
1%
#270000
0%
#275000
0G
1>
1E
0?
b1 (
b11 .
b1100 *
b1100 7
b1 -
b1010 ,
b1100 $
b1100 2
b1100 3
1C
b11100 )
b11100 A
0@
b1011 1
b1011 4
b1011 !
b1011 +
b1011 8
1%
#280000
0%
#285000
0'
b0 (
b0 .
b1101 *
b1101 7
b0 -
b1101 ,
b1101 $
b1101 2
b1101 3
0C
b1100 !
b1100 +
b1100 8
b1100 1
b1100 4
b11101 )
b11101 A
1@
1%
#290000
0%
#295000
0E
1?
b1 .
b1110 *
b1110 7
b1 -
b1100 ,
b1110 $
b1110 2
b1110 3
1C
b11110 )
b11110 A
0@
b1101 1
b1101 4
b1101 !
b1101 +
b1101 8
1%
#300000
0%
#305000
b0 .
b1111 *
b1111 7
b0 -
b1111 ,
b1111 $
b1111 2
b1111 3
0C
b1110 !
b1110 +
b1110 8
b1110 1
b1110 4
b11111 )
b11111 A
1@
1%
#310000
0%
#315000
0M
1;
b10 #
b10 0
b10 5
1K
0<
1I
0=
1G
0>
1E
0?
1'
b10011011 (
b111 .
b0 *
b0 7
b1 -
b1110 ,
b0 $
b0 2
b0 3
1C
b100000 )
b100000 A
0@
b1111 1
b1111 4
b1111 !
b1111 +
b1111 8
1%
#320000
0%
#325000
0'
b0 (
b10 *
b10 7
b0 .
b0 -
b10 ,
b1 $
b1 2
b1 3
0C
1"
b0 !
b0 +
b0 8
b10 /
b10 6
b0 1
b0 4
b100001 )
b100001 A
1@
1%
#330000
0%
#335000
0E
1?
b11 *
b11 7
b11 ,
b10 $
b10 2
b10 3
1C
b100010 )
b100010 A
0@
b1 1
b1 4
b10 !
b10 +
b10 8
0"
1%
#340000
0%
#345000
b10 .
b100 *
b100 7
b10 -
b0 ,
b11 $
b11 2
b11 3
0C
b11 !
b11 +
b11 8
b10 1
b10 4
b100011 )
b100011 A
1@
1%
#350000
0%
#355000
0G
1>
1E
0?
b101 *
b101 7
b1 ,
b100 $
b100 2
b100 3
1C
b100100 )
b100100 A
0@
b11 1
b11 4
b100 !
b100 +
b100 8
1%
#360000
0%
#365000
b0 .
b110 *
b110 7
b0 -
b110 ,
b101 $
b101 2
b101 3
0C
b101 !
b101 +
b101 8
b100 1
b100 4
b100101 )
b100101 A
1@
1%
#370000
0%
#375000
0E
1?
b111 *
b111 7
b111 ,
b110 $
b110 2
b110 3
1C
b100110 )
b100110 A
0@
b101 1
b101 4
b110 !
b110 +
b110 8
1%
#380000
0%
#385000
b110 .
b1100 (
b1000 *
b1000 7
b10 -
b100 ,
b111 $
b111 2
b111 3
0C
b111 !
b111 +
b111 8
b110 1
b110 4
b100111 )
b100111 A
1@
1%
#390000
0%
#395000
0I
1=
1G
0>
1E
0?
b1001 *
b1001 7
b101 ,
b1000 $
b1000 2
b1000 3
1C
b101000 )
b101000 A
0@
b111 1
b111 4
b1000 !
b1000 +
b1000 8
1%
#400000
0%
#405000
0'
b0 .
b0 (
b1010 *
b1010 7
b0 -
b1010 ,
b1001 $
b1001 2
b1001 3
0C
b1001 !
b1001 +
b1001 8
b1000 1
b1000 4
b101001 )
b101001 A
1@
1%
#410000
0%
#415000
0E
1?
b1011 *
b1011 7
b1011 ,
b1010 $
b1010 2
b1010 3
1C
b101010 )
b101010 A
0@
b1001 1
b1001 4
b1010 !
b1010 +
b1010 8
1%
#420000
0%
#425000
b10 .
b1100 *
b1100 7
b10 -
b1000 ,
b1011 $
b1011 2
b1011 3
0C
b1011 !
b1011 +
b1011 8
b1010 1
b1010 4
b101011 )
b101011 A
1@
1%
#430000
0%
#435000
0G
1>
1E
0?
b1101 *
b1101 7
b1001 ,
b1100 $
b1100 2
b1100 3
1C
b101100 )
b101100 A
0@
b1011 1
b1011 4
b1100 !
b1100 +
b1100 8
1%
#440000
0%
#445000
b0 .
b1110 *
b1110 7
b0 -
b1110 ,
b1101 $
b1101 2
b1101 3
0C
b1101 !
b1101 +
b1101 8
b1100 1
b1100 4
b101101 )
b101101 A
1@
1%
#450000
0%
#455000
0E
1?
b1111 *
b1111 7
b1111 ,
b1110 $
b1110 2
b1110 3
1C
b101110 )
b101110 A
0@
b1101 1
b1101 4
b1110 !
b1110 +
b1110 8
1%
#460000
0%
#465000
1'
b110 .
b10101100 (
b0 *
b0 7
b10 -
b1100 ,
b1111 $
b1111 2
b1111 3
0C
b1111 !
b1111 +
b1111 8
b1110 1
b1110 4
b101111 )
b101111 A
1@
1%
#470000
0%
#475000
b11 #
b11 0
b11 5
0K
1<
1I
0=
1G
0>
1E
0?
b1 *
b1 7
b1101 ,
b0 $
b0 2
b0 3
1C
b110000 )
b110000 A
0@
b1111 1
b1111 4
b0 !
b0 +
b0 8
1"
1%
#480000
0%
#485000
0'
b0 .
b0 (
b11 *
b11 7
b0 -
b11 ,
b1 $
b1 2
b1 3
0C
b1 !
b1 +
b1 8
b11 /
b11 6
b0 1
b0 4
b110001 )
b110001 A
1@
1%
#490000
0%
#495000
0E
1?
b1 (
b11 .
b100 *
b100 7
b1 -
b10 ,
b10 $
b10 2
b10 3
1C
b110010 )
b110010 A
0@
b1 1
b1 4
b11 !
b11 +
b11 8
0"
1%
#500000
0%
#505000
b0 (
b10 .
b101 *
b101 7
b10 -
b1 ,
b11 $
b11 2
b11 3
0C
b100 !
b100 +
b100 8
b10 1
b10 4
b110011 )
b110011 A
1@
1%
#510000
0%
#515000
0G
1>
1E
0?
b11 .
b110 *
b110 7
b11 -
b0 ,
b100 $
b100 2
b100 3
1C
b110100 )
b110100 A
0@
b11 1
b11 4
b101 !
b101 +
b101 8
1%
#520000
0%
#525000
b0 .
b111 *
b111 7
b0 -
b111 ,
b101 $
b101 2
b101 3
0C
b110 !
b110 +
b110 8
b100 1
b100 4
b110101 )
b110101 A
1@
1%
#530000
0%
#535000
0E
1?
b1011 (
b111 .
b1000 *
b1000 7
b1 -
b110 ,
b110 $
b110 2
b110 3
1C
b110110 )
b110110 A
0@
b101 1
b101 4
b111 !
b111 +
b111 8
1%
#540000
0%
#545000
b1100 (
b110 .
b1001 *
b1001 7
b10 -
b101 ,
b111 $
b111 2
b111 3
0C
b1000 !
b1000 +
b1000 8
b110 1
b110 4
b110111 )
b110111 A
1@
1%
#550000
0%
#555000
0I
1=
1G
0>
1E
0?
b111 .
b1010 *
b1010 7
b11 -
b100 ,
b1000 $
b1000 2
b1000 3
1C
b111000 )
b111000 A
0@
b111 1
b111 4
b1001 !
b1001 +
b1001 8
1%
#560000
0%
#565000
0'
b0 (
b0 .
b1011 *
b1011 7
b0 -
b1011 ,
b1001 $
b1001 2
b1001 3
0C
b1010 !
b1010 +
b1010 8
b1000 1
b1000 4
b111001 )
b111001 A
1@
1%
#570000
0%
#575000
0E
1?
b1 (
b11 .
b1100 *
b1100 7
b1 -
b1010 ,
b1010 $
b1010 2
b1010 3
1C
b111010 )
b111010 A
0@
b1001 1
b1001 4
b1011 !
b1011 +
b1011 8
1%
#580000
0%
#585000
b0 (
b10 .
b1101 *
b1101 7
b10 -
b1001 ,
b1011 $
b1011 2
b1011 3
0C
b1100 !
b1100 +
b1100 8
b1010 1
b1010 4
b111011 )
b111011 A
1@
1%
#590000
0%
#595000
0G
1>
1E
0?
b11 .
b1110 *
b1110 7
b11 -
b1000 ,
b1100 $
b1100 2
b1100 3
1C
b111100 )
b111100 A
0@
b1011 1
b1011 4
b1101 !
b1101 +
b1101 8
1%
#600000
0%
#605000
b0 .
b1111 *
b1111 7
b0 -
b1111 ,
b1101 $
b1101 2
b1101 3
0C
b1110 !
b1110 +
b1110 8
b1100 1
b1100 4
b111101 )
b111101 A
1@
1%
#610000
0%
#615000
0E
1?
1'
b10011011 (
b111 .
b0 *
b0 7
b1 -
b1110 ,
b1110 $
b1110 2
b1110 3
1C
b111110 )
b111110 A
0@
b1101 1
b1101 4
b1111 !
b1111 +
b1111 8
1%
#620000
0%
#625000
b10101100 (
b110 .
b1 *
b1 7
b10 -
b1101 ,
b1111 $
b1111 2
b1111 3
0C
1"
b0 !
b0 +
b0 8
b1110 1
b1110 4
b111111 )
b111111 A
1@
1%
#630000
0%
#635000
0O
1:
1M
0;
b100 #
b100 0
b100 5
1K
0<
1I
0=
1G
0>
1E
0?
b111 .
b10 *
b10 7
b11 -
b1100 ,
b0 $
b0 2
b0 3
1C
b1000000 )
b1000000 A
0@
b1111 1
b1111 4
b1 !
b1 +
b1 8
1%
#640000
0%
#645000
0'
b0 (
b100 *
b100 7
b0 .
b0 -
b100 ,
b1 $
b1 2
b1 3
0C
b10 !
b10 +
b10 8
b100 /
b100 6
b0 1
b0 4
b1000001 )
b1000001 A
1@
1%
#650000
0%
#655000
0E
1?
b101 *
b101 7
b101 ,
b10 $
b10 2
b10 3
1C
b1000010 )
b1000010 A
0@
b1 1
b1 4
b100 !
b100 +
b100 8
0"
1%
#660000
0%
#665000
b110 *
b110 7
b110 ,
b11 $
b11 2
b11 3
0C
b101 !
b101 +
b101 8
b10 1
b10 4
b1000011 )
b1000011 A
1@
1%
#670000
0%
#675000
0G
1>
1E
0?
b111 *
b111 7
b111 ,
b100 $
b100 2
b100 3
1C
b1000100 )
b1000100 A
0@
b11 1
b11 4
b110 !
b110 +
b110 8
1%
#680000
0%
#685000
b100 .
b1000 *
b1000 7
b100 -
b0 ,
b101 $
b101 2
b101 3
0C
b111 !
b111 +
b111 8
b100 1
b100 4
b1000101 )
b1000101 A
1@
1%
#690000
0%
#695000
0E
1?
b1001 *
b1001 7
b1 ,
b110 $
b110 2
b110 3
1C
b1000110 )
b1000110 A
0@
b101 1
b101 4
b1000 !
b1000 +
b1000 8
1%
#700000
0%
#705000
b1010 *
b1010 7
b10 ,
b111 $
b111 2
b111 3
0C
b1001 !
b1001 +
b1001 8
b110 1
b110 4
b1000111 )
b1000111 A
1@
1%
#710000
0%
#715000
0I
1=
1G
0>
1E
0?
b1011 *
b1011 7
b11 ,
b1000 $
b1000 2
b1000 3
1C
b1001000 )
b1001000 A
0@
b111 1
b111 4
b1010 !
b1010 +
b1010 8
1%
#720000
0%
#725000
b0 .
b1100 *
b1100 7
b0 -
b1100 ,
b1001 $
b1001 2
b1001 3
0C
b1011 !
b1011 +
b1011 8
b1000 1
b1000 4
b1001001 )
b1001001 A
1@
1%
#730000
0%
#735000
0E
1?
b1101 *
b1101 7
b1101 ,
b1010 $
b1010 2
b1010 3
1C
b1001010 )
b1001010 A
0@
b1001 1
b1001 4
b1100 !
b1100 +
b1100 8
1%
#740000
0%
#745000
b1110 *
b1110 7
b1110 ,
b1011 $
b1011 2
b1011 3
0C
b1101 !
b1101 +
b1101 8
b1010 1
b1010 4
b1001011 )
b1001011 A
1@
1%
#750000
0%
#755000
0G
1>
1E
0?
b1111 *
b1111 7
b1111 ,
b1100 $
b1100 2
b1100 3
1C
b1001100 )
b1001100 A
0@
b1011 1
b1011 4
b1110 !
b1110 +
b1110 8
1%
#760000
0%
#765000
1'
b100 .
b101000000 (
b0 *
b0 7
b100 -
b1000 ,
b1101 $
b1101 2
b1101 3
0C
b1111 !
b1111 +
b1111 8
b1100 1
b1100 4
b1001101 )
b1001101 A
1@
1%
#770000
0%
#775000
0E
1?
b1 *
b1 7
b1001 ,
b1110 $
b1110 2
b1110 3
1C
b1001110 )
b1001110 A
0@
b1101 1
b1101 4
b0 !
b0 +
b0 8
1"
1%
#780000
0%
#785000
b10 *
b10 7
b1010 ,
b1111 $
b1111 2
b1111 3
0C
b1 !
b1 +
b1 8
b1110 1
b1110 4
b1001111 )
b1001111 A
1@
1%
#790000
0%
#795000
b101 #
b101 0
b101 5
0K
1<
1I
0=
1G
0>
1E
0?
b11 *
b11 7
b1011 ,
b0 $
b0 2
b0 3
1C
b1010000 )
b1010000 A
0@
b1111 1
b1111 4
b10 !
b10 +
b10 8
1%
#800000
0%
#805000
0'
b0 .
b0 (
b101 *
b101 7
b0 -
b101 ,
b1 $
b1 2
b1 3
0C
b11 !
b11 +
b11 8
b101 /
b101 6
b0 1
b0 4
b1010001 )
b1010001 A
1@
1%
#810000
0%
#815000
0E
1?
b1 .
b110 *
b110 7
b1 -
b100 ,
b10 $
b10 2
b10 3
1C
b1010010 )
b1010010 A
0@
b1 1
b1 4
b101 !
b101 +
b101 8
0"
1%
#820000
0%
#825000
b0 .
b111 *
b111 7
b0 -
b111 ,
b11 $
b11 2
b11 3
0C
b110 !
b110 +
b110 8
b10 1
b10 4
b1010011 )
b1010011 A
1@
1%
#830000
0%
#835000
0G
1>
1E
0?
b1011 (
b111 .
b1000 *
b1000 7
b1 -
b110 ,
b100 $
b100 2
b100 3
1C
b1010100 )
b1010100 A
0@
b11 1
b11 4
b111 !
b111 +
b111 8
1%
#840000
0%
#845000
b0 (
b100 .
b1001 *
b1001 7
b100 -
b1 ,
b101 $
b101 2
b101 3
0C
b1000 !
b1000 +
b1000 8
b100 1
b100 4
b1010101 )
b1010101 A
1@
1%
#850000
0%
#855000
0E
1?
b101 .
b1010 *
b1010 7
b101 -
b0 ,
b110 $
b110 2
b110 3
1C
b1010110 )
b1010110 A
0@
b101 1
b101 4
b1001 !
b1001 +
b1001 8
1%
#860000
0%
#865000
b100 .
b1011 *
b1011 7
b100 -
b11 ,
b111 $
b111 2
b111 3
0C
b1010 !
b1010 +
b1010 8
b110 1
b110 4
b1010111 )
b1010111 A
1@
1%
#870000
0%
#875000
0I
1=
1G
0>
1E
0?
b1 (
b111 .
b1100 *
b1100 7
b101 -
b10 ,
b1000 $
b1000 2
b1000 3
1C
b1011000 )
b1011000 A
0@
b111 1
b111 4
b1011 !
b1011 +
b1011 8
1%
#880000
0%
#885000
0'
b0 (
b0 .
b1101 *
b1101 7
b0 -
b1101 ,
b1001 $
b1001 2
b1001 3
0C
b1100 !
b1100 +
b1100 8
b1000 1
b1000 4
b1011001 )
b1011001 A
1@
1%
#890000
0%
#895000
0E
1?
b1 .
b1110 *
b1110 7
b1 -
b1100 ,
b1010 $
b1010 2
b1010 3
1C
b1011010 )
b1011010 A
0@
b1001 1
b1001 4
b1101 !
b1101 +
b1101 8
1%
#900000
0%
#905000
b0 .
b1111 *
b1111 7
b0 -
b1111 ,
b1011 $
b1011 2
b1011 3
0C
b1110 !
b1110 +
b1110 8
b1010 1
b1010 4
b1011011 )
b1011011 A
1@
1%
#910000
0%
#915000
0G
1>
1E
0?
1'
b10011011 (
b111 .
b0 *
b0 7
b1 -
b1110 ,
b1100 $
b1100 2
b1100 3
1C
b1011100 )
b1011100 A
0@
b1011 1
b1011 4
b1111 !
b1111 +
b1111 8
1%
#920000
0%
#925000
b101000000 (
b100 .
b1 *
b1 7
b100 -
b1001 ,
b1101 $
b1101 2
b1101 3
0C
1"
b0 !
b0 +
b0 8
b1100 1
b1100 4
b1011101 )
b1011101 A
1@
1%
#930000
0%
#935000
0E
1?
b101 .
b10 *
b10 7
b101 -
b1000 ,
b1110 $
b1110 2
b1110 3
1C
b1011110 )
b1011110 A
0@
b1101 1
b1101 4
b1 !
b1 +
b1 8
1%
#940000
0%
#945000
b100 .
b11 *
b11 7
b100 -
b1011 ,
b1111 $
b1111 2
b1111 3
0C
b10 !
b10 +
b10 8
b1110 1
b1110 4
b1011111 )
b1011111 A
1@
1%
#950000
0%
#955000
0M
1;
b110 #
b110 0
b110 5
1K
0<
1I
0=
1G
0>
1E
0?
b101000001 (
b111 .
b100 *
b100 7
b101 -
b1010 ,
b0 $
b0 2
b0 3
1C
b1100000 )
b1100000 A
0@
b1111 1
b1111 4
b11 !
b11 +
b11 8
1%
#960000
0%
#965000
0'
b0 (
b110 *
b110 7
b0 .
b0 -
b110 ,
b1 $
b1 2
b1 3
0C
b100 !
b100 +
b100 8
b110 /
b110 6
b0 1
b0 4
b1100001 )
b1100001 A
1@
1%
#970000
0%
